Metadata-Version: 2.1
Name: runish
Version: 0.1
Summary: A Unicode name finder and characters explainer.
Home-page: https://github.com/facundobatista/runish
Author: Facundo Batista
Author-email: facundo@taniquetil.com.ar
License: GPL-v3
Platform: UNKNOWN
Classifier: Environment :: Console
Classifier: License :: OSI Approved :: GNU General Public License v3 (GPLv3)
Classifier: Operating System :: OS Independent
Classifier: Programming Language :: Python :: 3
Requires-Python: >=3
License-File: LICENSE
